sheet_loader/__init__.py
sheet_loader/buffer_processor.py
sheet_loader/connection.py
sheet_loader/detecting_buffer.py
sheet_loader/helpers.py
sheet_loader/py.typed
sheet_loader/sheet_loader.py
sheet_loader/types.py
sheet_loader-1.1.3.dist-info/LICENSE
sheet_loader-1.1.3.dist-info/WHEEL
sheet_loader-1.1.3.dist-info/METADATA
sheet_loader-1.1.3.dist-info/RECORD
