Metadata-Version: 2.1
Name: sheet-loader
Version: 1.1.3
Summary: Description
Home-page: https://github.com/mumblepins/sheet-loader/
License: LGPL-3.0-or-later
Author: Daniel Sullivan
Author-email: mumblepins@users.noreply.github.com
Requires-Python: >=3.8,<4.0
Classifier: License :: OSI Approved :: GNU Lesser General Public License v3 or later (LGPLv3+)
Classifier: Programming Language :: Python :: 3
Classifier: Programming Language :: Python :: 3.8
Classifier: Programming Language :: Python :: 3.9
Classifier: Programming Language :: Python :: 3.10
Provides-Extra: pandas
Requires-Dist: chardet
Requires-Dist: pandas; extra == "pandas"
Project-URL: Documentation, https://mumblepins.github.io/sheet-loader/
Project-URL: Repository, https://github.com/mumblepins/sheet-loader/
